{
  "Tournament": {
    "Date": "2024-05-19T00:00:00Z",
    "Name": "Pioneer League",
    "Uri": "https://www.mtgo.com/decklist/pioneer-league-2024-05-198099"
  },
  "Decks": [
    {
      "Date": "2024-05-19T00:00:00",
      "Player": "_Falcon_",
      "Result": "5-0",
      "AnchorUri": "https://www.mtgo.com/decklist/pioneer-league-2024-05-198099#deck__Falcon_",
      "Mainboard": [
        {
          "Count": 2,
          "CardName": "Bitter Triumph"
        },
        {
          "Count": 4,
          "CardName": "Blackcleave Cliffs"
        },
        {
          "Count": 4,
          "CardName": "Blightstep Pathway"
        },
        {
          "Count": 4,
          "CardName": "Blood Crypt"
        },
        {
          "Count": 4,
          "CardName": "Bloodtithe Harvester"
        },
        {
          "Count": 2,
          "CardName": "Duress"
        },
        {
          "Count": 4,
          "CardName": "Fable of the Mirror-Breaker"
        },
        {
          "Count": 4,
          "CardName": "Fatal Push"
        },
        {
          "Count": 2,
          "CardName": "Haunted Ridge"
        },
        {
          "Count": 2,
          "CardName": "Hive of the Eye Tyrant"
        },
        {
          "Count": 1,
          "CardName": "Kalitas, Traitor of Ghet"
        },
        {
          "Count": 4,
          "CardName": "Mutavault"
        },
        {
          "Count": 2,
          "CardName": "Preacher of the Schism"
        },
        {
          "Count": 1,
          "CardName": "Sheoldred, the Apocalypse"
        },
        {
          "Count": 2,
          "CardName": "Smuggler's Copter"
        },
        {
          "Count": 4,
          "CardName": "Sorin, Imperious Bloodlord"
        },
        {
          "Count": 3,
          "CardName": "Sulfurous Springs"
        },
        {
          "Count": 2,
          "CardName": "Swamp"
        },
        {
          "Count": 1,
          "CardName": "Takenuma, Abandoned Mire"
        },
        {
          "Count": 4,
          "CardName": "Thoughtseize"
        },
        {
          "Count": 4,
          "CardName": "Vein Ripper"
        }
      ],
      "Sideboard": [
        {
          "Count": 1,
          "CardName": "Ashiok, Dream Render"
        },
        {
          "Count": 2,
          "CardName": "Damping Sphere"
        },
        {
          "Count": 1,
          "CardName": "Duress"
        },
        {
          "Count": 4,
          "CardName": "Leyline of the Void"
        },
        {
          "Count": 2,
          "CardName": "Liliana of the Veil"
        },
        {
          "Count": 2,
          "CardName": "Path of Peril"
        },
        {
          "Count": 2,
          "CardName": "Reckoner Bankbuster"
        },
        {
          "Count": 1,
          "CardName": "Sheoldred's Edict"
        }
      ]
    },
    {
      "Date": "2024-05-19T00:00:00",
      "Player": "jackie42005",
      "Result": "5-0",
      "AnchorUri": "https://www.mtgo.com/decklist/pioneer-league-2024-05-198099#deck_jackie42005",
      "Mainboard": [
        {
          "Count": 4,
          "CardName": "Adeline, Resplendent Cathar"
        },
        {
          "Count": 4,
          "CardName": "Bloodsoaked Champion"
        },
        {
          "Count": 4,
          "CardName": "Brightclimb Pathway"
        },
        {
          "Count": 4,
          "CardName": "Caves of Koilos"
        },
        {
          "Count": 4,
          "CardName": "Concealed Courtyard"
        },
        {
          "Count": 2,
          "CardName": "Containment Priest"
        },
        {
          "Count": 4,
          "CardName": "Coppercoat Vanguard"
        },
        {
          "Count": 2,
          "CardName": "Dauntless Bodyguard"
        },
        {
          "Count": 4,
          "CardName": "Dire Tactics"
        },
        {
          "Count": 2,
          "CardName": "Eiganjo, Seat of the Empire"
        },
        {
          "Count": 1,
          "CardName": "General Kudro of Drannith"
        },
        {
          "Count": 1,
          "CardName": "Get Lost"
        },
        {
          "Count": 1,
          "CardName": "Giant Killer"
        },
        {
          "Count": 4,
          "CardName": "Godless Shrine"
        },
        {
          "Count": 1,
          "CardName": "Graveyard Trespasser"
        },
        {
          "Count": 2,
          "CardName": "Hopeful Initiate"
        },
        {
          "Count": 2,
          "CardName": "Kytheon, Hero of Akros"
        },
        {
          "Count": 4,
          "CardName": "Mutavault"
        },
        {
          "Count": 2,
          "CardName": "Recruitment Officer"
        },
        {
          "Count": 4,
          "CardName": "Thalia, Guardian of Thraben"
        },
        {
          "Count": 4,
          "CardName": "Thalia's Lieutenant"
        }
      ],
      "Sideboard": [
        {
          "Count": 2,
          "CardName": "Aven Interrupter"
        },
        {
          "Count": 4,
          "CardName": "Fatal Push"
        },
        {
          "Count": 1,
          "CardName": "Graveyard Trespasser"
        },
        {
          "Count": 4,
          "CardName": "Knight of Dusk's Shadow"
        },
        {
          "Count": 4,
          "CardName": "Thoughtseize"
        }
      ]
    },
    {
      "Date": "2024-05-19T00:00:00",
      "Player": "ZephyrBro",
      "Result": "5-0",
      "AnchorUri": "https://www.mtgo.com/decklist/pioneer-league-2024-05-198099#deck_ZephyrBro",
      "Mainboard": [
        {
          "Count": 1,
          "CardName": "Castle Ardenvale"
        },
        {
          "Count": 1,
          "CardName": "Castle Vantress"
        },
        {
          "Count": 2,
          "CardName": "Censor"
        },
        {
          "Count": 1,
          "CardName": "Day's Undoing"
        },
        {
          "Count": 1,
          "CardName": "Deduce"
        },
        {
          "Count": 3,
          "CardName": "Deserted Beach"
        },
        {
          "Count": 3,
          "CardName": "Dovin's Veto"
        },
        {
          "Count": 1,
          "CardName": "Eiganjo, Seat of the Empire"
        },
        {
          "Count": 3,
          "CardName": "Field of Ruin"
        },
        {
          "Count": 1,
          "CardName": "Geier Reach Sanitarium"
        },
        {
          "Count": 1,
          "CardName": "Get Lost"
        },
        {
          "Count": 1,
          "CardName": "Hall of Storm Giants"
        },
        {
          "Count": 4,
          "CardName": "Hallowed Fountain"
        },
        {
          "Count": 3,
          "CardName": "Island"
        },
        {
          "Count": 1,
          "CardName": "Jwari Disruption"
        },
        {
          "Count": 2,
          "CardName": "March of Otherworldly Light"
        },
        {
          "Count": 2,
          "CardName": "Memory Deluge"
        },
        {
          "Count": 3,
          "CardName": "Narset, Parter of Veils"
        },
        {
          "Count": 4,
          "CardName": "No More Lies"
        },
        {
          "Count": 1,
          "CardName": "Otawara, Soaring City"
        },
        {
          "Count": 3,
          "CardName": "Plains"
        },
        {
          "Count": 2,
          "CardName": "Portable Hole"
        },
        {
          "Count": 2,
          "CardName": "Restless Anchorage"
        },
        {
          "Count": 3,
          "CardName": "Sunfall"
        },
        {
          "Count": 2,
          "CardName": "Sunken Citadel"
        },
        {
          "Count": 2,
          "CardName": "Supreme Verdict"
        },
        {
          "Count": 2,
          "CardName": "Teferi, Hero of Dominaria"
        },
        {
          "Count": 3,
          "CardName": "The Wandering Emperor"
        },
        {
          "Count": 2,
          "CardName": "Three Steps Ahead"
        }
      ],
      "Sideboard": [
        {
          "Count": 1,
          "CardName": "Farewell"
        },
        {
          "Count": 1,
          "CardName": "Kaheera, the Orphanguard"
        },
        {
          "Count": 2,
          "CardName": "Kutzil's Flanker"
        },
        {
          "Count": 4,
          "CardName": "Mystical Dispute"
        },
        {
          "Count": 1,
          "CardName": "Portable Hole"
        },
        {
          "Count": 2,
          "CardName": "Regal Caracal"
        },
        {
          "Count": 2,
          "CardName": "Rest in Peace"
        },
        {
          "Count": 2,
          "CardName": "Shark Typhoon"
        }
      ]
    },
    {
      "Date": "2024-05-19T00:00:00",
      "Player": "Wuggltugglyo",
      "Result": "5-0",
      "AnchorUri": "https://www.mtgo.com/decklist/pioneer-league-2024-05-198099#deck_Wuggltugglyo",
      "Mainboard": [
        {
          "Count": 3,
          "CardName": "Archfiend of the Dross"
        },
        {
          "Count": 1,
          "CardName": "Bitter Triumph"
        },
        {
          "Count": 4,
          "CardName": "Blackcleave Cliffs"
        },
        {
          "Count": 2,
          "CardName": "Blightstep Pathway"
        },
        {
          "Count": 4,
          "CardName": "Blood Crypt"
        },
        {
          "Count": 4,
          "CardName": "Bloodtithe Harvester"
        },
        {
          "Count": 1,
          "CardName": "Cavern of Souls"
        },
        {
          "Count": 1,
          "CardName": "Duress"
        },
        {
          "Count": 3,
          "CardName": "Dusk Legion Zealot"
        },
        {
          "Count": 4,
          "CardName": "Fable of the Mirror-Breaker"
        },
        {
          "Count": 4,
          "CardName": "Fatal Push"
        },
        {
          "Count": 1,
          "CardName": "Heartless Act"
        },
        {
          "Count": 2,
          "CardName": "Hive of the Eye Tyrant"
        },
        {
          "Count": 1,
          "CardName": "Kolaghan's Command"
        },
        {
          "Count": 4,
          "CardName": "Mutavault"
        },
        {
          "Count": 2,
          "CardName": "Preacher of the Schism"
        },
        {
          "Count": 4,
          "CardName": "Sorin, Imperious Bloodlord"
        },
        {
          "Count": 3,
          "CardName": "Sulfurous Springs"
        },
        {
          "Count": 3,
          "CardName": "Swamp"
        },
        {
          "Count": 1,
          "CardName": "Takenuma, Abandoned Mire"
        },
        {
          "Count": 4,
          "CardName": "Thoughtseize"
        },
        {
          "Count": 4,
          "CardName": "Vein Ripper"
        }
      ],
      "Sideboard": [
        {
          "Count": 2,
          "CardName": "Damping Sphere"
        },
        {
          "Count": 1,
          "CardName": "Duress"
        },
        {
          "Count": 2,
          "CardName": "Grafdigger's Cage"
        },
        {
          "Count": 1,
          "CardName": "Kolaghan's Command"
        },
        {
          "Count": 4,
          "CardName": "Leyline of the Void"
        },
        {
          "Count": 2,
          "CardName": "Liliana of the Veil"
        },
        {
          "Count": 1,
          "CardName": "Sheoldred's Edict"
        },
        {
          "Count": 2,
          "CardName": "Unlicensed Hearse"
        }
      ]
    },
    {
      "Date": "2024-05-19T00:00:00",
      "Player": "drcheez",
      "Result": "5-0",
      "AnchorUri": "https://www.mtgo.com/decklist/pioneer-league-2024-05-198099#deck_drcheez",
      "Mainboard": [
        {
          "Count": 1,
          "CardName": "Aetherflux Reservoir"
        },
        {
          "Count": 4,
          "CardName": "Amalia Benavides Aguirre"
        },
        {
          "Count": 3,
          "CardName": "Blooming Marsh"
        },
        {
          "Count": 1,
          "CardName": "Boseiju, Who Endures"
        },
        {
          "Count": 1,
          "CardName": "Cenote Scout"
        },
        {
          "Count": 4,
          "CardName": "Chord of Calling"
        },
        {
          "Count": 3,
          "CardName": "Collected Company"
        },
        {
          "Count": 2,
          "CardName": "Deep-Cavern Bat"
        },
        {
          "Count": 1,
          "CardName": "Dina, Soul Steeper"
        },
        {
          "Count": 2,
          "CardName": "Extraction Specialist"
        },
        {
          "Count": 2,
          "CardName": "Fauna Shaman"
        },
        {
          "Count": 3,
          "CardName": "Lunarch Veteran"
        },
        {
          "Count": 4,
          "CardName": "Mana Confluence"
        },
        {
          "Count": 4,
          "CardName": "Overgrown Tomb"
        },
        {
          "Count": 1,
          "CardName": "Plains"
        },
        {
          "Count": 4,
          "CardName": "Prosperous Innkeeper"
        },
        {
          "Count": 4,
          "CardName": "Razorverge Thicket"
        },
        {
          "Count": 2,
          "CardName": "Return to the Ranks"
        },
        {
          "Count": 2,
          "CardName": "Selfless Savior"
        },
        {
          "Count": 2,
          "CardName": "Sentinel of the Nameless City"
        },
        {
          "Count": 1,
          "CardName": "Skyclave Apparition"
        },
        {
          "Count": 1,
          "CardName": "Takenuma, Abandoned Mire"
        },
        {
          "Count": 4,
          "CardName": "Temple Garden"
        },
        {
          "Count": 4,
          "CardName": "Wildgrowth Walker"
        }
      ],
      "Sideboard": [
        {
          "Count": 1,
          "CardName": "Archon of Emeria"
        },
        {
          "Count": 2,
          "CardName": "Assassin's Trophy"
        },
        {
          "Count": 1,
          "CardName": "Aven Interrupter"
        },
        {
          "Count": 2,
          "CardName": "Fatal Push"
        },
        {
          "Count": 1,
          "CardName": "Haywire Mite"
        },
        {
          "Count": 1,
          "CardName": "Knight of Dusk's Shadow"
        },
        {
          "Count": 1,
          "CardName": "Ruthless Lawbringer"
        },
        {
          "Count": 2,
          "CardName": "Tamiyo's Safekeeping"
        },
        {
          "Count": 2,
          "CardName": "Thoughtseize"
        },
        {
          "Count": 1,
          "CardName": "Thrun, Breaker of Silence"
        },
        {
          "Count": 1,
          "CardName": "Vivien, Monsters' Advocate"
        }
      ]
    },
    {
      "Date": "2024-05-19T00:00:00",
      "Player": "CrazyMorango",
      "Result": "5-0",
      "AnchorUri": "https://www.mtgo.com/decklist/pioneer-league-2024-05-198099#deck_CrazyMorango",
      "Mainboard": [
        {
          "Count": 2,
          "CardName": "Bitter Triumph"
        },
        {
          "Count": 4,
          "CardName": "Blackcleave Cliffs"
        },
        {
          "Count": 3,
          "CardName": "Blightstep Pathway"
        },
        {
          "Count": 4,
          "CardName": "Blood Crypt"
        },
        {
          "Count": 4,
          "CardName": "Bloodtithe Harvester"
        },
        {
          "Count": 1,
          "CardName": "Duress"
        },
        {
          "Count": 3,
          "CardName": "Dusk Legion Zealot"
        },
        {
          "Count": 4,
          "CardName": "Fable of the Mirror-Breaker"
        },
        {
          "Count": 4,
          "CardName": "Fatal Push"
        },
        {
          "Count": 2,
          "CardName": "Hive of the Eye Tyrant"
        },
        {
          "Count": 1,
          "CardName": "Kalitas, Traitor of Ghet"
        },
        {
          "Count": 1,
          "CardName": "Mountain"
        },
        {
          "Count": 4,
          "CardName": "Mutavault"
        },
        {
          "Count": 3,
          "CardName": "Preacher of the Schism"
        },
        {
          "Count": 1,
          "CardName": "Sheoldred, the Apocalypse"
        },
        {
          "Count": 4,
          "CardName": "Sorin, Imperious Bloodlord"
        },
        {
          "Count": 4,
          "CardName": "Sulfurous Springs"
        },
        {
          "Count": 2,
          "CardName": "Swamp"
        },
        {
          "Count": 1,
          "CardName": "Takenuma, Abandoned Mire"
        },
        {
          "Count": 4,
          "CardName": "Thoughtseize"
        },
        {
          "Count": 4,
          "CardName": "Vein Ripper"
        }
      ],
      "Sideboard": [
        {
          "Count": 1,
          "CardName": "Blot Out"
        },
        {
          "Count": 2,
          "CardName": "Duress"
        },
        {
          "Count": 1,
          "CardName": "Grafdigger's Cage"
        },
        {
          "Count": 1,
          "CardName": "Knight of Dusk's Shadow"
        },
        {
          "Count": 4,
          "CardName": "Leyline of the Void"
        },
        {
          "Count": 2,
          "CardName": "Liliana of the Veil"
        },
        {
          "Count": 2,
          "CardName": "Necromentia"
        },
        {
          "Count": 2,
          "CardName": "Path of Peril"
        }
      ]
    },
    {
      "Date": "2024-05-19T00:00:00",
      "Player": "Trey29tyson",
      "Result": "5-0",
      "AnchorUri": "https://www.mtgo.com/decklist/pioneer-league-2024-05-198099#deck_Trey29tyson",
      "Mainboard": [
        {
          "Count": 3,
          "CardName": "Den of the Bugbear"
        },
        {
          "Count": 4,
          "CardName": "Ghitu Lavarunner"
        },
        {
          "Count": 4,
          "CardName": "Kumano Faces Kakkazan"
        },
        {
          "Count": 4,
          "CardName": "Light Up the Stage"
        },
        {
          "Count": 4,
          "CardName": "Monastery Swiftspear"
        },
        {
          "Count": 4,
          "CardName": "Monstrous Rage"
        },
        {
          "Count": 11,
          "CardName": "Mountain"
        },
        {
          "Count": 4,
          "CardName": "Play with Fire"
        },
        {
          "Count": 4,
          "CardName": "Ramunap Ruins"
        },
        {
          "Count": 4,
          "CardName": "Skewer the Critics"
        },
        {
          "Count": 4,
          "CardName": "Slickshot Show-Off"
        },
        {
          "Count": 4,
          "CardName": "Soul-Scar Mage"
        },
        {
          "Count": 2,
          "CardName": "Spikefield Hazard"
        },
        {
          "Count": 4,
          "CardName": "Wizard's Lightning"
        }
      ],
      "Sideboard": [
        {
          "Count": 3,
          "CardName": "Case of the Crimson Pulse"
        },
        {
          "Count": 2,
          "CardName": "Chandra's Defeat"
        },
        {
          "Count": 3,
          "CardName": "Rampaging Ferocidon"
        },
        {
          "Count": 1,
          "CardName": "Redcap Melee"
        },
        {
          "Count": 2,
          "CardName": "Rending Volley"
        },
        {
          "Count": 2,
          "CardName": "Tears of Valakut"
        },
        {
          "Count": 2,
          "CardName": "Witchstalker Frenzy"
        }
      ]
    },
    {
      "Date": "2024-05-19T00:00:00",
      "Player": "lain5893",
      "Result": "5-0",
      "AnchorUri": "https://www.mtgo.com/decklist/pioneer-league-2024-05-198099#deck_lain5893",
      "Mainboard": [
        {
          "Count": 4,
          "CardName": "Aloe Alchemist"
        },
        {
          "Count": 4,
          "CardName": "Atarka's Command"
        },
        {
          "Count": 4,
          "CardName": "Burning-Tree Emissary"
        },
        {
          "Count": 4,
          "CardName": "Cacophony Scamp"
        },
        {
          "Count": 4,
          "CardName": "Copperline Gorge"
        },
        {
          "Count": 3,
          "CardName": "Cragcrown Pathway"
        },
        {
          "Count": 4,
          "CardName": "Cunning Coyote"
        },
        {
          "Count": 4,
          "CardName": "Karplusan Forest"
        },
        {
          "Count": 4,
          "CardName": "Kumano Faces Kakkazan"
        },
        {
          "Count": 4,
          "CardName": "Legion Loyalist"
        },
        {
          "Count": 4,
          "CardName": "Monstrous Rage"
        },
        {
          "Count": 1,
          "CardName": "Mountain"
        },
        {
          "Count": 4,
          "CardName": "Phoenix Chick"
        },
        {
          "Count": 4,
          "CardName": "Ramunap Ruins"
        },
        {
          "Count": 4,
          "CardName": "Reckless Bushwhacker"
        },
        {
          "Count": 4,
          "CardName": "Stomping Ground"
        }
      ],
      "Sideboard": [
        {
          "Count": 3,
          "CardName": "Pick Your Poison"
        },
        {
          "Count": 3,
          "CardName": "Rampaging Ferocidon"
        },
        {
          "Count": 3,
          "CardName": "Redcap Melee"
        },
        {
          "Count": 3,
          "CardName": "Rending Volley"
        },
        {
          "Count": 3,
          "CardName": "Urabrask's Forge"
        }
      ]
    },
    {
      "Date": "2024-05-19T00:00:00",
      "Player": "Fink64",
      "Result": "5-0",
      "AnchorUri": "https://www.mtgo.com/decklist/pioneer-league-2024-05-198099#deck_Fink64",
      "Mainboard": [
        {
          "Count": 4,
          "CardName": "Case of the Filched Falcon"
        },
        {
          "Count": 4,
          "CardName": "Darksteel Citadel"
        },
        {
          "Count": 2,
          "CardName": "Diamond Pick-Axe"
        },
        {
          "Count": 4,
          "CardName": "Ensoul Artifact"
        },
        {
          "Count": 4,
          "CardName": "Gleaming Geardrake"
        },
        {
          "Count": 1,
          "CardName": "Island"
        },
        {
          "Count": 4,
          "CardName": "Metallic Rebuke"
        },
        {
          "Count": 1,
          "CardName": "Mountain"
        },
        {
          "Count": 1,
          "CardName": "Otawara, Soaring City"
        },
        {
          "Count": 2,
          "CardName": "Riverglide Pathway"
        },
        {
          "Count": 4,
          "CardName": "Shivan Reef"
        },
        {
          "Count": 4,
          "CardName": "Shrapnel Blast"
        },
        {
          "Count": 2,
          "CardName": "Smuggler's Copter"
        },
        {
          "Count": 1,
          "CardName": "Sokenzan, Crucible of Defiance"
        },
        {
          "Count": 4,
          "CardName": "Spirebluff Canal"
        },
        {
          "Count": 4,
          "CardName": "Spyglass Siren"
        },
        {
          "Count": 4,
          "CardName": "Steam Vents"
        },
        {
          "Count": 4,
          "CardName": "Torch the Tower"
        },
        {
          "Count": 4,
          "CardName": "Voldaren Epicure"
        },
        {
          "Count": 2,
          "CardName": "Zoetic Glyph"
        }
      ],
      "Sideboard": [
        {
          "Count": 1,
          "CardName": "Jegantha, the Wellspring"
        },
        {
          "Count": 2,
          "CardName": "Rampaging Ferocidon"
        },
        {
          "Count": 4,
          "CardName": "Spell Pierce"
        },
        {
          "Count": 2,
          "CardName": "Tears of Valakut"
        },
        {
          "Count": 2,
          "CardName": "Unlicensed Hearse"
        },
        {
          "Count": 4,
          "CardName": "Voltage Surge"
        }
      ]
    },
    {
      "Date": "2024-05-19T00:00:00",
      "Player": "HEROtsukai",
      "Result": "5-0",
      "AnchorUri": "https://www.mtgo.com/decklist/pioneer-league-2024-05-198099#deck_HEROtsukai",
      "Mainboard": [
        {
          "Count": 4,
          "CardName": "Ascendant Spirit"
        },
        {
          "Count": 1,
          "CardName": "Brazen Borrower"
        },
        {
          "Count": 3,
          "CardName": "Cryptic Coat"
        },
        {
          "Count": 4,
          "CardName": "Curious Obsession"
        },
        {
          "Count": 3,
          "CardName": "Faceless Haven"
        },
        {
          "Count": 4,
          "CardName": "Geistlight Snare"
        },
        {
          "Count": 4,
          "CardName": "Mausoleum Wanderer"
        },
        {
          "Count": 1,
          "CardName": "Otawara, Soaring City"
        },
        {
          "Count": 4,
          "CardName": "Rattlechains"
        },
        {
          "Count": 4,
          "CardName": "Shacklegeist"
        },
        {
          "Count": 18,
          "CardName": "Snow-Covered Island"
        },
        {
          "Count": 4,
          "CardName": "Spectral Sailor"
        },
        {
          "Count": 2,
          "CardName": "Spell Pierce"
        },
        {
          "Count": 4,
          "CardName": "Supreme Phantom"
        }
      ],
      "Sideboard": [
        {
          "Count": 1,
          "CardName": "Brazen Borrower"
        },
        {
          "Count": 1,
          "CardName": "Faceless Haven"
        },
        {
          "Count": 3,
          "CardName": "Lofty Denial"
        },
        {
          "Count": 1,
          "CardName": "Miscast"
        },
        {
          "Count": 4,
          "CardName": "Mystical Dispute"
        },
        {
          "Count": 2,
          "CardName": "Reckoner Bankbuster"
        },
        {
          "Count": 3,
          "CardName": "Unlicensed Hearse"
        }
      ]
    },
    {
      "Date": "2024-05-19T00:00:00",
      "Player": "taku123",
      "Result": "5-0",
      "AnchorUri": "https://www.mtgo.com/decklist/pioneer-league-2024-05-198099#deck_taku123",
      "Mainboard": [
        {
          "Count": 4,
          "CardName": "Beanstalk Giant"
        },
        {
          "Count": 4,
          "CardName": "Bedeck // Bedazzle"
        },
        {
          "Count": 3,
          "CardName": "Blood Crypt"
        },
        {
          "Count": 2,
          "CardName": "Boseiju, Who Endures"
        },
        {
          "Count": 3,
          "CardName": "Breach the Multiverse"
        },
        {
          "Count": 2,
          "CardName": "Forest"
        },
        {
          "Count": 4,
          "CardName": "Greater Tanuki"
        },
        {
          "Count": 2,
          "CardName": "Indatha Triome"
        },
        {
          "Count": 1,
          "CardName": "Island"
        },
        {
          "Count": 2,
          "CardName": "Isolated Chapel"
        },
        {
          "Count": 2,
          "CardName": "Jetmir's Garden"
        },
        {
          "Count": 4,
          "CardName": "Leyline Binding"
        },
        {
          "Count": 2,
          "CardName": "Mountain"
        },
        {
          "Count": 3,
          "CardName": "Overgrown Tomb"
        },
        {
          "Count": 2,
          "CardName": "Plains"
        },
        {
          "Count": 4,
          "CardName": "Quintorius Kand"
        },
        {
          "Count": 2,
          "CardName": "Release to the Wind"
        },
        {
          "Count": 2,
          "CardName": "Rootbound Crag"
        },
        {
          "Count": 3,
          "CardName": "Shefet Monitor"
        },
        {
          "Count": 2,
          "CardName": "Spara's Headquarters"
        },
        {
          "Count": 4,
          "CardName": "Spark Double"
        },
        {
          "Count": 4,
          "CardName": "Spinewoods Armadillo"
        },
        {
          "Count": 3,
          "CardName": "Stomping Ground"
        },
        {
          "Count": 2,
          "CardName": "Swamp"
        },
        {
          "Count": 1,
          "CardName": "Temple Garden"
        },
        {
          "Count": 4,
          "CardName": "Trumpeting Carnosaur"
        },
        {
          "Count": 1,
          "CardName": "Urborg, Tomb of Yawgmoth"
        },
        {
          "Count": 4,
          "CardName": "Virtue of Persistence"
        },
        {
          "Count": 2,
          "CardName": "Zagoth Triome"
        },
        {
          "Count": 2,
          "CardName": "Ziatora's Proving Ground"
        }
      ],
      "Sideboard": [
        {
          "Count": 2,
          "CardName": "Krenko's Buzzcrusher"
        },
        {
          "Count": 4,
          "CardName": "Quakebringer"
        },
        {
          "Count": 4,
          "CardName": "Rags // Riches"
        },
        {
          "Count": 4,
          "CardName": "Thought Distortion"
        },
        {
          "Count": 1,
          "CardName": "Yorion, Sky Nomad"
        }
      ]
    },
    {
      "Date": "2024-05-19T00:00:00",
      "Player": "lain5893",
      "Result": "5-0",
      "AnchorUri": "https://www.mtgo.com/decklist/pioneer-league-2024-05-198099#deck_lain5893",
      "Mainboard": [
        {
          "Count": 4,
          "CardName": "Aloe Alchemist"
        },
        {
          "Count": 4,
          "CardName": "Atarka's Command"
        },
        {
          "Count": 4,
          "CardName": "Burning-Tree Emissary"
        },
        {
          "Count": 4,
          "CardName": "Cacophony Scamp"
        },
        {
          "Count": 4,
          "CardName": "Copperline Gorge"
        },
        {
          "Count": 3,
          "CardName": "Cragcrown Pathway"
        },
        {
          "Count": 4,
          "CardName": "Cunning Coyote"
        },
        {
          "Count": 4,
          "CardName": "Karplusan Forest"
        },
        {
          "Count": 4,
          "CardName": "Kumano Faces Kakkazan"
        },
        {
          "Count": 4,
          "CardName": "Legion Loyalist"
        },
        {
          "Count": 4,
          "CardName": "Monstrous Rage"
        },
        {
          "Count": 1,
          "CardName": "Mountain"
        },
        {
          "Count": 4,
          "CardName": "Phoenix Chick"
        },
        {
          "Count": 4,
          "CardName": "Ramunap Ruins"
        },
        {
          "Count": 4,
          "CardName": "Reckless Bushwhacker"
        },
        {
          "Count": 4,
          "CardName": "Stomping Ground"
        }
      ],
      "Sideboard": [
        {
          "Count": 3,
          "CardName": "Kari Zev's Expertise"
        },
        {
          "Count": 3,
          "CardName": "Redcap Melee"
        },
        {
          "Count": 3,
          "CardName": "Rending Volley"
        },
        {
          "Count": 3,
          "CardName": "Unlicensed Hearse"
        },
        {
          "Count": 3,
          "CardName": "Urabrask's Forge"
        }
      ]
    },
    {
      "Date": "2024-05-19T00:00:00",
      "Player": "Aerien_sol",
      "Result": "5-0",
      "AnchorUri": "https://www.mtgo.com/decklist/pioneer-league-2024-05-198099#deck_Aerien_sol",
      "Mainboard": [
        {
          "Count": 1,
          "CardName": "Aetherflux Reservoir"
        },
        {
          "Count": 4,
          "CardName": "Amalia Benavides Aguirre"
        },
        {
          "Count": 3,
          "CardName": "Blooming Marsh"
        },
        {
          "Count": 2,
          "CardName": "Boseiju, Who Endures"
        },
        {
          "Count": 1,
          "CardName": "Cenote Scout"
        },
        {
          "Count": 4,
          "CardName": "Chord of Calling"
        },
        {
          "Count": 3,
          "CardName": "Collected Company"
        },
        {
          "Count": 2,
          "CardName": "Deep-Cavern Bat"
        },
        {
          "Count": 1,
          "CardName": "Dina, Soul Steeper"
        },
        {
          "Count": 2,
          "CardName": "Extraction Specialist"
        },
        {
          "Count": 2,
          "CardName": "Fauna Shaman"
        },
        {
          "Count": 3,
          "CardName": "Lunarch Veteran"
        },
        {
          "Count": 4,
          "CardName": "Mana Confluence"
        },
        {
          "Count": 3,
          "CardName": "Overgrown Tomb"
        },
        {
          "Count": 1,
          "CardName": "Plains"
        },
        {
          "Count": 4,
          "CardName": "Prosperous Innkeeper"
        },
        {
          "Count": 4,
          "CardName": "Razorverge Thicket"
        },
        {
          "Count": 2,
          "CardName": "Return to the Ranks"
        },
        {
          "Count": 2,
          "CardName": "Selfless Savior"
        },
        {
          "Count": 2,
          "CardName": "Sentinel of the Nameless City"
        },
        {
          "Count": 1,
          "CardName": "Skyclave Apparition"
        },
        {
          "Count": 1,
          "CardName": "Takenuma, Abandoned Mire"
        },
        {
          "Count": 4,
          "CardName": "Temple Garden"
        },
        {
          "Count": 4,
          "CardName": "Wildgrowth Walker"
        }
      ],
      "Sideboard": [
        {
          "Count": 1,
          "CardName": "Deep-Cavern Bat"
        },
        {
          "Count": 2,
          "CardName": "Fatal Push"
        },
        {
          "Count": 2,
          "CardName": "Get Lost"
        },
        {
          "Count": 1,
          "CardName": "Haywire Mite"
        },
        {
          "Count": 1,
          "CardName": "Knight of Dusk's Shadow"
        },
        {
          "Count": 1,
          "CardName": "Reidane, God of the Worthy"
        },
        {
          "Count": 1,
          "CardName": "Remorseful Cleric"
        },
        {
          "Count": 1,
          "CardName": "Skyclave Apparition"
        },
        {
          "Count": 2,
          "CardName": "Tamiyo's Safekeeping"
        },
        {
          "Count": 3,
          "CardName": "Thoughtseize"
        }
      ]
    },
    {
      "Date": "2024-05-19T00:00:00",
      "Player": "_Cygnus",
      "Result": "5-0",
      "AnchorUri": "https://www.mtgo.com/decklist/pioneer-league-2024-05-198099#deck__Cygnus",
      "Mainboard": [
        {
          "Count": 4,
          "CardName": "Adeline, Resplendent Cathar"
        },
        {
          "Count": 2,
          "CardName": "Anointed Peacekeeper"
        },
        {
          "Count": 4,
          "CardName": "Cavern of Souls"
        },
        {
          "Count": 4,
          "CardName": "Coppercoat Vanguard"
        },
        {
          "Count": 4,
          "CardName": "Dauntless Bodyguard"
        },
        {
          "Count": 2,
          "CardName": "Eiganjo, Seat of the Empire"
        },
        {
          "Count": 2,
          "CardName": "Extraction Specialist"
        },
        {
          "Count": 4,
          "CardName": "Get Lost"
        },
        {
          "Count": 4,
          "CardName": "Hopeful Initiate"
        },
        {
          "Count": 2,
          "CardName": "Kytheon, Hero of Akros"
        },
        {
          "Count": 4,
          "CardName": "Mutavault"
        },
        {
          "Count": 12,
          "CardName": "Plains"
        },
        {
          "Count": 4,
          "CardName": "Recruitment Officer"
        },
        {
          "Count": 4,
          "CardName": "Thalia, Guardian of Thraben"
        },
        {
          "Count": 4,
          "CardName": "Thalia's Lieutenant"
        }
      ],
      "Sideboard": [
        {
          "Count": 2,
          "CardName": "Anointed Peacekeeper"
        },
        {
          "Count": 3,
          "CardName": "Brutal Cathar"
        },
        {
          "Count": 4,
          "CardName": "Containment Priest"
        },
        {
          "Count": 2,
          "CardName": "Extraction Specialist"
        },
        {
          "Count": 4,
          "CardName": "Portable Hole"
        }
      ]
    },
    {
      "Date": "2024-05-19T00:00:00",
      "Player": "shenyang45",
      "Result": "5-0",
      "AnchorUri": "https://www.mtgo.com/decklist/pioneer-league-2024-05-198099#deck_shenyang45",
      "Mainboard": [
        {
          "Count": 1,
          "CardName": "Aetherflux Reservoir"
        },
        {
          "Count": 4,
          "CardName": "Amalia Benavides Aguirre"
        },
        {
          "Count": 3,
          "CardName": "Blooming Marsh"
        },
        {
          "Count": 1,
          "CardName": "Boseiju, Who Endures"
        },
        {
          "Count": 2,
          "CardName": "Cenote Scout"
        },
        {
          "Count": 4,
          "CardName": "Chord of Calling"
        },
        {
          "Count": 3,
          "CardName": "Collected Company"
        },
        {
          "Count": 1,
          "CardName": "Concealed Courtyard"
        },
        {
          "Count": 2,
          "CardName": "Deep-Cavern Bat"
        },
        {
          "Count": 1,
          "CardName": "Dina, Soul Steeper"
        },
        {
          "Count": 2,
          "CardName": "Extraction Specialist"
        },
        {
          "Count": 2,
          "CardName": "Fauna Shaman"
        },
        {
          "Count": 3,
          "CardName": "Lunarch Veteran"
        },
        {
          "Count": 4,
          "CardName": "Mana Confluence"
        },
        {
          "Count": 3,
          "CardName": "Overgrown Tomb"
        },
        {
          "Count": 1,
          "CardName": "Plains"
        },
        {
          "Count": 4,
          "CardName": "Prosperous Innkeeper"
        },
        {
          "Count": 3,
          "CardName": "Razorverge Thicket"
        },
        {
          "Count": 3,
          "CardName": "Return to the Ranks"
        },
        {
          "Count": 1,
          "CardName": "Scattered Groves"
        },
        {
          "Count": 1,
          "CardName": "Scavenging Ooze"
        },
        {
          "Count": 1,
          "CardName": "Selfless Savior"
        },
        {
          "Count": 1,
          "CardName": "Skyclave Apparition"
        },
        {
          "Count": 1,
          "CardName": "Takenuma, Abandoned Mire"
        },
        {
          "Count": 4,
          "CardName": "Temple Garden"
        },
        {
          "Count": 4,
          "CardName": "Wildgrowth Walker"
        }
      ],
      "Sideboard": [
        {
          "Count": 2,
          "CardName": "Fatal Push"
        },
        {
          "Count": 2,
          "CardName": "Get Lost"
        },
        {
          "Count": 1,
          "CardName": "Haywire Mite"
        },
        {
          "Count": 1,
          "CardName": "Jirina, Dauntless General"
        },
        {
          "Count": 1,
          "CardName": "Knight of Dusk's Shadow"
        },
        {
          "Count": 1,
          "CardName": "Loran of the Third Path"
        },
        {
          "Count": 1,
          "CardName": "Reidane, God of the Worthy"
        },
        {
          "Count": 1,
          "CardName": "Ruthless Lawbringer"
        },
        {
          "Count": 2,
          "CardName": "Sentinel of the Nameless City"
        },
        {
          "Count": 1,
          "CardName": "Tamiyo's Safekeeping"
        },
        {
          "Count": 2,
          "CardName": "Thoughtseize"
        }
      ]
    },
    {
      "Date": "2024-05-19T00:00:00",
      "Player": "Coly2",
      "Result": "5-0",
      "AnchorUri": "https://www.mtgo.com/decklist/pioneer-league-2024-05-198099#deck_Coly2",
      "Mainboard": [
        {
          "Count": 2,
          "CardName": "Boseiju, Who Endures"
        },
        {
          "Count": 2,
          "CardName": "Castle Garenbrig"
        },
        {
          "Count": 4,
          "CardName": "Cavalier of Thorns"
        },
        {
          "Count": 2,
          "CardName": "Elder Gargaroth"
        },
        {
          "Count": 4,
          "CardName": "Elvish Mystic"
        },
        {
          "Count": 9,
          "CardName": "Forest"
        },
        {
          "Count": 3,
          "CardName": "Invasion of Ixalan"
        },
        {
          "Count": 4,
          "CardName": "Kiora, Behemoth Beckoner"
        },
        {
          "Count": 2,
          "CardName": "Lair of the Hydra"
        },
        {
          "Count": 4,
          "CardName": "Leyline of the Guildpact"
        },
        {
          "Count": 4,
          "CardName": "Llanowar Elves"
        },
        {
          "Count": 4,
          "CardName": "Nykthos, Shrine to Nyx"
        },
        {
          "Count": 1,
          "CardName": "Oath of Nissa"
        },
        {
          "Count": 4,
          "CardName": "Old-Growth Troll"
        },
        {
          "Count": 4,
          "CardName": "Outcaster Trailblazer"
        },
        {
          "Count": 1,
          "CardName": "Polukranos Reborn"
        },
        {
          "Count": 4,
          "CardName": "Storm the Festival"
        },
        {
          "Count": 2,
          "CardName": "Sunken Citadel"
        },
        {
          "Count": 1,
          "CardName": "Ulvenwald Oddity"
        }
      ],
      "Sideboard": [
        {
          "Count": 2,
          "CardName": "Damping Sphere"
        },
        {
          "Count": 3,
          "CardName": "Gather Courage"
        },
        {
          "Count": 3,
          "CardName": "Pick Your Poison"
        },
        {
          "Count": 2,
          "CardName": "Tail Swipe"
        },
        {
          "Count": 3,
          "CardName": "The Stone Brain"
        },
        {
          "Count": 2,
          "CardName": "Unlicensed Hearse"
        }
      ]
    },
    {
      "Date": "2024-05-19T00:00:00",
      "Player": "StanUA",
      "Result": "5-0",
      "AnchorUri": "https://www.mtgo.com/decklist/pioneer-league-2024-05-198099#deck_StanUA",
      "Mainboard": [
        {
          "Count": 4,
          "CardName": "Arclight Phoenix"
        },
        {
          "Count": 1,
          "CardName": "Brazen Borrower"
        },
        {
          "Count": 4,
          "CardName": "Consider"
        },
        {
          "Count": 3,
          "CardName": "Fiery Impulse"
        },
        {
          "Count": 1,
          "CardName": "Galvanic Iteration"
        },
        {
          "Count": 2,
          "CardName": "Hall of Storm Giants"
        },
        {
          "Count": 3,
          "CardName": "Island"
        },
        {
          "Count": 4,
          "CardName": "Ledger Shredder"
        },
        {
          "Count": 4,
          "CardName": "Lightning Axe"
        },
        {
          "Count": 4,
          "CardName": "Opt"
        },
        {
          "Count": 1,
          "CardName": "Otawara, Soaring City"
        },
        {
          "Count": 4,
          "CardName": "Picklock Prankster"
        },
        {
          "Count": 4,
          "CardName": "Riverglide Pathway"
        },
        {
          "Count": 4,
          "CardName": "Sleight of Hand"
        },
        {
          "Count": 3,
          "CardName": "Spell Pierce"
        },
        {
          "Count": 4,
          "CardName": "Spirebluff Canal"
        },
        {
          "Count": 4,
          "CardName": "Steam Vents"
        },
        {
          "Count": 1,
          "CardName": "Stormcarved Coast"
        },
        {
          "Count": 1,
          "CardName": "Temporal Trespass"
        },
        {
          "Count": 4,
          "CardName": "Treasure Cruise"
        }
      ],
      "Sideboard": [
        {
          "Count": 1,
          "CardName": "Aether Gust"
        },
        {
          "Count": 2,
          "CardName": "Anger of the Gods"
        },
        {
          "Count": 1,
          "CardName": "Ashiok, Dream Render"
        },
        {
          "Count": 1,
          "CardName": "Beacon Bolt"
        },
        {
          "Count": 2,
          "CardName": "Crackling Drake"
        },
        {
          "Count": 1,
          "CardName": "Fable of the Mirror-Breaker"
        },
        {
          "Count": 2,
          "CardName": "Mystical Dispute"
        },
        {
          "Count": 2,
          "CardName": "Negate"
        },
        {
          "Count": 1,
          "CardName": "Unlicensed Hearse"
        },
        {
          "Count": 2,
          "CardName": "Young Pyromancer"
        }
      ]
    },
    {
      "Date": "2024-05-19T00:00:00",
      "Player": "Olivetti",
      "Result": "5-0",
      "AnchorUri": "https://www.mtgo.com/decklist/pioneer-league-2024-05-198099#deck_Olivetti",
      "Mainboard": [
        {
          "Count": 2,
          "CardName": "Ancient Cornucopia"
        },
        {
          "Count": 2,
          "CardName": "Blood Crypt"
        },
        {
          "Count": 1,
          "CardName": "Breeding Pool"
        },
        {
          "Count": 4,
          "CardName": "Bring to Light"
        },
        {
          "Count": 1,
          "CardName": "Consecrate // Consume"
        },
        {
          "Count": 1,
          "CardName": "Deadly Cover-Up"
        },
        {
          "Count": 1,
          "CardName": "Deafening Clarion"
        },
        {
          "Count": 4,
          "CardName": "Fable of the Mirror-Breaker"
        },
        {
          "Count": 4,
          "CardName": "Fabled Passage"
        },
        {
          "Count": 1,
          "CardName": "Forest"
        },
        {
          "Count": 1,
          "CardName": "Godless Shrine"
        },
        {
          "Count": 2,
          "CardName": "Hallowed Fountain"
        },
        {
          "Count": 3,
          "CardName": "Indatha Triome"
        },
        {
          "Count": 1,
          "CardName": "Island"
        },
        {
          "Count": 2,
          "CardName": "Jetmir's Garden"
        },
        {
          "Count": 2,
          "CardName": "Ketria Triome"
        },
        {
          "Count": 1,
          "CardName": "Klothys, God of Destiny"
        },
        {
          "Count": 1,
          "CardName": "Kolaghan's Command"
        },
        {
          "Count": 4,
          "CardName": "Leyline Binding"
        },
        {
          "Count": 3,
          "CardName": "Lightning Helix"
        },
        {
          "Count": 1,
          "CardName": "Lilah, Undefeated Slickshot"
        },
        {
          "Count": 1,
          "CardName": "Mana Confluence"
        },
        {
          "Count": 1,
          "CardName": "Molten Collapse"
        },
        {
          "Count": 1,
          "CardName": "Mountain"
        },
        {
          "Count": 2,
          "CardName": "Niv-Mizzet Reborn"
        },
        {
          "Count": 1,
          "CardName": "Niv-Mizzet, Supreme"
        },
        {
          "Count": 3,
          "CardName": "Omnath, Locus of Creation"
        },
        {
          "Count": 2,
          "CardName": "Pillage the Bog"
        },
        {
          "Count": 1,
          "CardName": "Plains"
        },
        {
          "Count": 1,
          "CardName": "Raffine's Tower"
        },
        {
          "Count": 1,
          "CardName": "Savai Triome"
        },
        {
          "Count": 1,
          "CardName": "Spara's Headquarters"
        },
        {
          "Count": 2,
          "CardName": "Steam Vents"
        },
        {
          "Count": 1,
          "CardName": "Stomping Ground"
        },
        {
          "Count": 1,
          "CardName": "Sunfall"
        },
        {
          "Count": 1,
          "CardName": "Sunpetal Grove"
        },
        {
          "Count": 1,
          "CardName": "Swamp"
        },
        {
          "Count": 4,
          "CardName": "Sylvan Caryatid"
        },
        {
          "Count": 1,
          "CardName": "Temple Garden"
        },
        {
          "Count": 1,
          "CardName": "Unmoored Ego"
        },
        {
          "Count": 4,
          "CardName": "Up the Beanstalk"
        },
        {
          "Count": 1,
          "CardName": "Valki, God of Lies"
        },
        {
          "Count": 3,
          "CardName": "Vanishing Verse"
        },
        {
          "Count": 2,
          "CardName": "Watery Grave"
        },
        {
          "Count": 1,
          "CardName": "Ziatora's Proving Ground"
        }
      ],
      "Sideboard": [
        {
          "Count": 2,
          "CardName": "Ashiok, Dream Render"
        },
        {
          "Count": 1,
          "CardName": "Consecrate // Consume"
        },
        {
          "Count": 2,
          "CardName": "Damping Sphere"
        },
        {
          "Count": 1,
          "CardName": "Dovin's Veto"
        },
        {
          "Count": 2,
          "CardName": "Kambal, Consul of Allocation"
        },
        {
          "Count": 1,
          "CardName": "Krenko's Buzzcrusher"
        },
        {
          "Count": 1,
          "CardName": "Lightning Helix"
        },
        {
          "Count": 1,
          "CardName": "Quakebringer"
        },
        {
          "Count": 2,
          "CardName": "Soul Search"
        },
        {
          "Count": 1,
          "CardName": "Sunfall"
        },
        {
          "Count": 1,
          "CardName": "Yorion, Sky Nomad"
        }
      ]
    },
    {
      "Date": "2024-05-19T00:00:00",
      "Player": "gabbii_",
      "Result": "5-0",
      "AnchorUri": "https://www.mtgo.com/decklist/pioneer-league-2024-05-198099#deck_gabbii_",
      "Mainboard": [
        {
          "Count": 4,
          "CardName": "Case of the Filched Falcon"
        },
        {
          "Count": 4,
          "CardName": "Darksteel Citadel"
        },
        {
          "Count": 2,
          "CardName": "Diamond Pick-Axe"
        },
        {
          "Count": 4,
          "CardName": "Ensoul Artifact"
        },
        {
          "Count": 4,
          "CardName": "Gleaming Geardrake"
        },
        {
          "Count": 1,
          "CardName": "Island"
        },
        {
          "Count": 4,
          "CardName": "Metallic Rebuke"
        },
        {
          "Count": 1,
          "CardName": "Mountain"
        },
        {
          "Count": 1,
          "CardName": "Otawara, Soaring City"
        },
        {
          "Count": 2,
          "CardName": "Riverglide Pathway"
        },
        {
          "Count": 4,
          "CardName": "Shivan Reef"
        },
        {
          "Count": 4,
          "CardName": "Shrapnel Blast"
        },
        {
          "Count": 2,
          "CardName": "Smuggler's Copter"
        },
        {
          "Count": 1,
          "CardName": "Sokenzan, Crucible of Defiance"
        },
        {
          "Count": 4,
          "CardName": "Spirebluff Canal"
        },
        {
          "Count": 4,
          "CardName": "Spyglass Siren"
        },
        {
          "Count": 4,
          "CardName": "Steam Vents"
        },
        {
          "Count": 4,
          "CardName": "Torch the Tower"
        },
        {
          "Count": 4,
          "CardName": "Voldaren Epicure"
        },
        {
          "Count": 2,
          "CardName": "Zoetic Glyph"
        }
      ],
      "Sideboard": [
        {
          "Count": 1,
          "CardName": "Jegantha, the Wellspring"
        },
        {
          "Count": 2,
          "CardName": "Rampaging Ferocidon"
        },
        {
          "Count": 4,
          "CardName": "Spell Pierce"
        },
        {
          "Count": 2,
          "CardName": "Tears of Valakut"
        },
        {
          "Count": 2,
          "CardName": "Unlicensed Hearse"
        },
        {
          "Count": 4,
          "CardName": "Voltage Surge"
        }
      ]
    },
    {
      "Date": "2024-05-19T00:00:00",
      "Player": "brunoprince",
      "Result": "5-0",
      "AnchorUri": "https://www.mtgo.com/decklist/pioneer-league-2024-05-198099#deck_brunoprince",
      "Mainboard": [
        {
          "Count": 1,
          "CardName": "Aclazotz, Deepest Betrayal"
        },
        {
          "Count": 1,
          "CardName": "Blast Zone"
        },
        {
          "Count": 3,
          "CardName": "Castle Locthwain"
        },
        {
          "Count": 1,
          "CardName": "Cling to Dust"
        },
        {
          "Count": 2,
          "CardName": "Duress"
        },
        {
          "Count": 1,
          "CardName": "Extinction Event"
        },
        {
          "Count": 4,
          "CardName": "Fatal Push"
        },
        {
          "Count": 3,
          "CardName": "Field of Ruin"
        },
        {
          "Count": 3,
          "CardName": "Geier Reach Sanitarium"
        },
        {
          "Count": 4,
          "CardName": "Go Blank"
        },
        {
          "Count": 1,
          "CardName": "Go for the Throat"
        },
        {
          "Count": 2,
          "CardName": "Hive of the Eye Tyrant"
        },
        {
          "Count": 2,
          "CardName": "Hostile Investigator"
        },
        {
          "Count": 4,
          "CardName": "Liliana of the Veil"
        },
        {
          "Count": 1,
          "CardName": "Reckoner Bankbuster"
        },
        {
          "Count": 3,
          "CardName": "Sheoldred, the Apocalypse"
        },
        {
          "Count": 3,
          "CardName": "Sheoldred's Edict"
        },
        {
          "Count": 2,
          "CardName": "Sunken Citadel"
        },
        {
          "Count": 10,
          "CardName": "Swamp"
        },
        {
          "Count": 4,
          "CardName": "Thoughtseize"
        },
        {
          "Count": 1,
          "CardName": "Urborg, Tomb of Yawgmoth"
        },
        {
          "Count": 4,
          "CardName": "Waste Not"
        }
      ],
      "Sideboard": [
        {
          "Count": 1,
          "CardName": "Ashiok, Dream Render"
        },
        {
          "Count": 2,
          "CardName": "Cut Down"
        },
        {
          "Count": 1,
          "CardName": "Damping Sphere"
        },
        {
          "Count": 1,
          "CardName": "Davriel, Rogue Shadowmage"
        },
        {
          "Count": 1,
          "CardName": "Extinction Event"
        },
        {
          "Count": 2,
          "CardName": "Invoke Despair"
        },
        {
          "Count": 1,
          "CardName": "Knight of Dusk's Shadow"
        },
        {
          "Count": 3,
          "CardName": "Path of Peril"
        },
        {
          "Count": 2,
          "CardName": "Reckoner Bankbuster"
        },
        {
          "Count": 1,
          "CardName": "Unlicensed Hearse"
        }
      ]
    },
    {
      "Date": "2024-05-19T00:00:00",
      "Player": "S1fall0r",
      "Result": "5-0",
      "AnchorUri": "https://www.mtgo.com/decklist/pioneer-league-2024-05-198099#deck_S1fall0r",
      "Mainboard": [
        {
          "Count": 2,
          "CardName": "Archfiend of the Dross"
        },
        {
          "Count": 2,
          "CardName": "Bitter Triumph"
        },
        {
          "Count": 3,
          "CardName": "Blackcleave Cliffs"
        },
        {
          "Count": 2,
          "CardName": "Blightstep Pathway"
        },
        {
          "Count": 4,
          "CardName": "Blood Crypt"
        },
        {
          "Count": 4,
          "CardName": "Bloodtithe Harvester"
        },
        {
          "Count": 3,
          "CardName": "Cavern of Souls"
        },
        {
          "Count": 1,
          "CardName": "Duress"
        },
        {
          "Count": 3,
          "CardName": "Dusk Legion Zealot"
        },
        {
          "Count": 4,
          "CardName": "Fable of the Mirror-Breaker"
        },
        {
          "Count": 4,
          "CardName": "Fatal Push"
        },
        {
          "Count": 2,
          "CardName": "Hive of the Eye Tyrant"
        },
        {
          "Count": 4,
          "CardName": "Mutavault"
        },
        {
          "Count": 3,
          "CardName": "Preacher of the Schism"
        },
        {
          "Count": 1,
          "CardName": "Sokenzan, Crucible of Defiance"
        },
        {
          "Count": 4,
          "CardName": "Sorin, Imperious Bloodlord"
        },
        {
          "Count": 2,
          "CardName": "Sulfurous Springs"
        },
        {
          "Count": 2,
          "CardName": "Swamp"
        },
        {
          "Count": 1,
          "CardName": "Takenuma, Abandoned Mire"
        },
        {
          "Count": 4,
          "CardName": "Thoughtseize"
        },
        {
          "Count": 1,
          "CardName": "Urborg, Tomb of Yawgmoth"
        },
        {
          "Count": 4,
          "CardName": "Vein Ripper"
        }
      ],
      "Sideboard": [
        {
          "Count": 1,
          "CardName": "Ashiok, Dream Render"
        },
        {
          "Count": 2,
          "CardName": "Blot Out"
        },
        {
          "Count": 2,
          "CardName": "Damping Sphere"
        },
        {
          "Count": 2,
          "CardName": "Duress"
        },
        {
          "Count": 2,
          "CardName": "Extinction Event"
        },
        {
          "Count": 1,
          "CardName": "Go Blank"
        },
        {
          "Count": 1,
          "CardName": "Grafdigger's Cage"
        },
        {
          "Count": 1,
          "CardName": "Liliana of the Veil"
        },
        {
          "Count": 2,
          "CardName": "Path of Peril"
        },
        {
          "Count": 1,
          "CardName": "Unlicensed Hearse"
        }
      ]
    },
    {
      "Date": "2024-05-19T00:00:00",
      "Player": "CrazyMorango",
      "Result": "5-0",
      "AnchorUri": "https://www.mtgo.com/decklist/pioneer-league-2024-05-198099#deck_CrazyMorango",
      "Mainboard": [
        {
          "Count": 2,
          "CardName": "Bitter Triumph"
        },
        {
          "Count": 4,
          "CardName": "Blackcleave Cliffs"
        },
        {
          "Count": 3,
          "CardName": "Blightstep Pathway"
        },
        {
          "Count": 4,
          "CardName": "Blood Crypt"
        },
        {
          "Count": 4,
          "CardName": "Bloodtithe Harvester"
        },
        {
          "Count": 1,
          "CardName": "Duress"
        },
        {
          "Count": 3,
          "CardName": "Dusk Legion Zealot"
        },
        {
          "Count": 4,
          "CardName": "Fable of the Mirror-Breaker"
        },
        {
          "Count": 4,
          "CardName": "Fatal Push"
        },
        {
          "Count": 2,
          "CardName": "Hive of the Eye Tyrant"
        },
        {
          "Count": 1,
          "CardName": "Kalitas, Traitor of Ghet"
        },
        {
          "Count": 1,
          "CardName": "Mountain"
        },
        {
          "Count": 4,
          "CardName": "Mutavault"
        },
        {
          "Count": 3,
          "CardName": "Preacher of the Schism"
        },
        {
          "Count": 1,
          "CardName": "Sheoldred, the Apocalypse"
        },
        {
          "Count": 4,
          "CardName": "Sorin, Imperious Bloodlord"
        },
        {
          "Count": 4,
          "CardName": "Sulfurous Springs"
        },
        {
          "Count": 2,
          "CardName": "Swamp"
        },
        {
          "Count": 1,
          "CardName": "Takenuma, Abandoned Mire"
        },
        {
          "Count": 4,
          "CardName": "Thoughtseize"
        },
        {
          "Count": 4,
          "CardName": "Vein Ripper"
        }
      ],
      "Sideboard": [
        {
          "Count": 1,
          "CardName": "Blot Out"
        },
        {
          "Count": 2,
          "CardName": "Duress"
        },
        {
          "Count": 1,
          "CardName": "Grafdigger's Cage"
        },
        {
          "Count": 1,
          "CardName": "Knight of Dusk's Shadow"
        },
        {
          "Count": 4,
          "CardName": "Leyline of the Void"
        },
        {
          "Count": 2,
          "CardName": "Liliana of the Veil"
        },
        {
          "Count": 2,
          "CardName": "Necromentia"
        },
        {
          "Count": 2,
          "CardName": "Path of Peril"
        }
      ]
    }
  ],
  "Rounds": null,
  "Standings": null
}